MANIFEST.in
setup.py
django_grappelli_template_editor.egg-info/PKG-INFO
django_grappelli_template_editor.egg-info/SOURCES.txt
django_grappelli_template_editor.egg-info/dependency_links.txt
django_grappelli_template_editor.egg-info/not-zip-safe
django_grappelli_template_editor.egg-info/requires.txt
django_grappelli_template_editor.egg-info/top_level.txt
grappelli_te/__init__.py
grappelli_te/urls.py
grappelli_te/views.py
grappelli_te/static/grappelli_te/codemirror/lib/codemirror.css
grappelli_te/static/grappelli_te/codemirror/lib/codemirror.js
grappelli_te/static/grappelli_te/codemirror/mode/meta.js
grappelli_te/static/grappelli_te/codemirror/mode/css/css.js
grappelli_te/static/grappelli_te/codemirror/mode/css/index.html
grappelli_te/static/grappelli_te/codemirror/mode/css/less.html
grappelli_te/static/grappelli_te/codemirror/mode/css/less_test.js
grappelli_te/static/grappelli_te/codemirror/mode/css/scss.html
grappelli_te/static/grappelli_te/codemirror/mode/css/scss_test.js
grappelli_te/static/grappelli_te/codemirror/mode/css/test.js
grappelli_te/static/grappelli_te/codemirror/mode/django/django.js
grappelli_te/static/grappelli_te/codemirror/mode/django/index.html
grappelli_te/static/grappelli_te/codemirror/mode/htmlembedded/htmlembedded.js
grappelli_te/static/grappelli_te/codemirror/mode/htmlembedded/index.html
grappelli_te/static/grappelli_te/codemirror/mode/htmlmixed/htmlmixed.js
grappelli_te/static/grappelli_te/codemirror/mode/htmlmixed/index.html
grappelli_te/static/grappelli_te/codemirror/mode/javascript/index.html
grappelli_te/static/grappelli_te/codemirror/mode/javascript/javascript.js
grappelli_te/static/grappelli_te/codemirror/mode/javascript/json-ld.html
grappelli_te/static/grappelli_te/codemirror/mode/javascript/test.js
grappelli_te/static/grappelli_te/codemirror/mode/javascript/typescript.html
grappelli_te/static/grappelli_te/codemirror/mode/python/index.html
grappelli_te/static/grappelli_te/codemirror/mode/python/python.js
grappelli_te/static/grappelli_te/codemirror/mode/xml/index.html
grappelli_te/static/grappelli_te/codemirror/mode/xml/test.js
grappelli_te/static/grappelli_te/codemirror/mode/xml/xml.js
grappelli_te/static/grappelli_te/codemirror/theme/3024-day.css
grappelli_te/static/grappelli_te/codemirror/theme/3024-night.css
