Metadata-Version: 1.1
Name: django-grappelli-template-editor
Version: 0.3
Summary: A TTW Template Editor for Grappelli
Home-page: http://github.com/funkybob/django-grappelli-template-editor
Author: Curtis Maloney
Author-email: curtis@tinbrain.net
License: UNKNOWN
Keywords: django,grappelli
Platform: UNKNOWN
Classifier: Environment :: Web Environment
Classifier: Framework :: Django
Classifier: License :: OSI Approved :: BSD License
Classifier: Operating System :: OS Independent
Classifier: Programming Language :: Python
Requires: Django (>=1.6)
